crunchy_api/__init__.py
crunchy_api/cli.py
crunchy_api/types.py
crunchy_api-0.3.0.dist-info/entry_points.txt
crunchy_api-0.3.0.dist-info/LICENSE
crunchy_api-0.3.0.dist-info/WHEEL
crunchy_api-0.3.0.dist-info/METADATA
crunchy_api-0.3.0.dist-info/RECORD
