Metadata-Version: 2.1
Name: crunchy-api
Version: 0.3.0
Summary: Python wrapper for the Crunchyroll API
Home-page: https://github.com/buckley-w-david/crunchy-api
License: MIT
Author: David Buckley
Author-email: buckley.w.david@gmail.com
Requires-Python: >=3.6,<4.0
Classifier: License :: OSI Approved :: MIT License
Classifier: Programming Language :: Python :: 3
Classifier: Programming Language :: Python :: 3.6
Classifier: Programming Language :: Python :: 3.7
Provides-Extra: cli
Requires-Dist: click (>=6.7,<7.0); extra == "cli"
